pycons3rtapi/VERSION.txt
pycons3rtapi/__init__.py
pycons3rtapi/cons3rt.py
pycons3rtapi/cons3rtapi.py
pycons3rtapi/cons3rtcli.py
pycons3rtapi/cons3rtclient.py
pycons3rtapi/cons3rtconfig.py
pycons3rtapi/httpclient.py
pycons3rtapi/pycons3rtlibs.py
pycons3rtapi-0.0.12.dist-info/AUTHORS.txt
pycons3rtapi-0.0.12.dist-info/LICENSE
pycons3rtapi-0.0.12.dist-info/METADATA
pycons3rtapi-0.0.12.dist-info/WHEEL
pycons3rtapi-0.0.12.dist-info/entry_points.txt
pycons3rtapi-0.0.12.dist-info/top_level.txt
pycons3rtapi-0.0.12.dist-info/zip-safe
pycons3rtapi-0.0.12.dist-info/RECORD
