Metadata-Version: 2.1
Name: pycons3rtapi
Version: 0.0.12
Summary: Python API for CONS3RT
Home-page: https://github.com/cons3rt/pycons3rtapi
Author: Joe Yennaco
Author-email: joe.yennaco@jackpinetech.com
License: GNU GPL v3
Platform: UNKNOWN
Classifier: Programming Language :: Python :: 2.7
Classifier: Operating System :: OS Independent
Requires-Dist: requests-toolbelt
Requires-Dist: pycons3rt
